{
  "apiVersion": "2.145.3",
  "reference": "266929d7-c658-4c32-ab69-81f44a675c8d",
  "url": "urn:test",
  "title": null,
  "contentType": "text/plain",
  "language": "en",
  "databaseLabel": "Growth Cosmetic Ingredients and Substances",
  "database": "GROWTH_COSING",
  "summary": "",
  "weight": 8.456885,
  "groupById": null,
  "content": "",
  "accessRestriction": false,
  "pages": null,
  "checksum": "E3B0C44298FC1C149AFBF4C8996FB92427AE41E4649B934CA495991B7852B855",
  "metadata": {
    "nameOfCommonIngredientsGlossary": [
      "BIS-HYDROXYETHOXYPROPYL DIMETHICONE/LACTIDE COPOLYMER"
    ],
    "otherRestrictions": [],
    "note": [],
    "refNo": [],
    "sccsOpinionUrls": [],
    "innName": [],
    "other": [],
    "itemType": [
      "ingredient"
    ],
    "chemicalName": [
      "Siloxanes and Silicones, diMe, 3hydroxypropyl groupterminated, ethoxylated, diesters with (3S,6S)3,6dimethyl1,4dioxane2,5dione homopolymer"
    ],
    "sccsOpinion": [],
    "refNo_letter": [],
    "language": [
      "en"
    ],
    "chemicalDescription": [
      "Bis-Hydroxyethoxypropyl Dimethicone/Lactide Copolymer is the copolymer formed by the reaction of Bis-Hydroxyethoxypropyl Dimethicone with Lactide."
    ],
    "esST_checksum": [
      "E3B0C44298FC1C149AFBF4C8996FB92427AE41E4649B934CA495991B7852B855"
    ],
    "reference": [
      "773FC7A65CC5BDCD5324B69E5987B727"
    ],
    "cosmeticRestriction": [],
    "ecNo": [],
    "maximumConcentration": [],
    "identifiedIngredient": [],
    "officialJournalPublication": [
      "Y"
    ],
    "inciName": [
      "BIS-HYDROXYETHOXYPROPYL DIMETHICONE/LACTIDE COPOLYMER"
    ],
    "esST_FileName": [
      "file.txt"
    ],
    "casNo": [
      "1810718-57-0"
    ],
    "substanceId": [
      "94596"
    ],
    "DATASOURCE": [
      "GROWTH_COSING"
    ],
    "annexNo": [],
    "productTypeBodyParts": [],
    "phEurName": [],
    "es_ContentType": [
      "text/plain"
    ],
    "otherRegulations": [],
    "classificationInformation": [
      "[]"
    ],
    "functionName": [
      "BINDING",
      "BULKING",
      "SKIN CONDITIONING - EMOLLIENT",
      "FILM FORMING",
      "SKIN CONDITIONING"
    ],
    "esDA_IngestDate": [
      "2023-05-22T16:51:01.062+0200"
    ],
    "currentVersion": [],
    "corporate-search-version": [
      "102"
    ],
    "url": [
      "urn:test"
    ],
    "esST_URL": [
      "urn:test"
    ],
    "esDA_QueueDate": [
      "2023-05-22T16:51:01.029+0200"
    ],
    "refNo_digit": [],
    "colour": [],
    "datasource": [
      "GROWTH_COSING"
    ],
    "wordingOfConditions": [],
    "inciUsaName": [],
    "relatedRegulations": [],
    "perfuming": [
      "N"
    ],
    "status": [
      "Active"
    ]
  },
  "enrichedMetadata": {},
  "children": [],
  "highlightedFragments": []
}