{
  "apiVersion": "2.145.3",
  "reference": "32182c5e-0152-4d4c-8ce6-862e273a68c1",
  "url": "urn:test",
  "title": null,
  "contentType": "text/plain",
  "language": "en",
  "databaseLabel": "Growth Cosmetic Ingredients and Substances",
  "database": "GROWTH_COSING",
  "summary": "",
  "weight": 9.305475,
  "groupById": null,
  "content": "",
  "accessRestriction": false,
  "pages": null,
  "checksum": "E3B0C44298FC1C149AFBF4C8996FB92427AE41E4649B934CA495991B7852B855",
  "metadata": {
    "nameOfCommonIngredientsGlossary": [
      "Trisiloxylpropyl PEG-8 PEG-7 Glycol Succinyl Methyl Soyate"
    ],
    "refNo": [],
    "otherRestrictions": [],
    "note": [],
    "sccsOpinionUrls": [],
    "itemType": [
      "ingredient"
    ],
    "other": [],
    "innName": [],
    "chemicalName": [],
    "sccsOpinion": [],
    "refNo_letter": [],
    "language": [
      "en"
    ],
    "chemicalDescription": [
      "Trisiloxylpropyl PEG-8 PEG-7 Glycol Succinyl Methyl Soyate is the synthetic polymer that conforms generally to the formula, where the value of x is 7-9 and the value of y+z is 4-7 and R is methyl soyate."
    ],
    "esST_checksum": [
      "E3B0C44298FC1C149AFBF4C8996FB92427AE41E4649B934CA495991B7852B855"
    ],
    "reference": [
      "88ba588d-7179-4ad3-b3ac-6cec7d3db0ac"
    ],
    "cosmeticRestriction": [],
    "ecNo": [],
    "maximumConcentration": [],
    "identifiedIngredient": [],
    "inciName": [
      "TRISILOXYLPROPYL PEG-8 PEG-7 GLYCOL SUCCINYL METHYL SOYATE"
    ],
    "officialJournalPublication": [
      "Y"
    ],
    "esST_FileName": [
      "file.txt"
    ],
    "casNo": [],
    "substanceId": [
      "105037"
    ],
    "DATASOURCE": [
      "GROWTH_COSING"
    ],
    "REFERENCE": [
      "32182c5e-0152-4d4c-8ce6-862e273a68c1"
    ],
    "productTypeBodyParts": [],
    "annexNo": [],
    "phEurName": [],
    "es_ContentType": [
      "text/plain"
    ],
    "otherRegulations": [],
    "classificationInformation": [
      "[]"
    ],
    "functionName": [
      "SURFACTANT - EMULSIFYING",
      "EMULSION STABILISING"
    ],
    "esDA_IngestDate": [
      "2024-08-07T16:46:16.544+0200"
    ],
    "currentVersion": [],
    "url": [
      "urn:test"
    ],
    "esST_URL": [
      "urn:test"
    ],
    "esDA_QueueDate": [
      "2024-08-07T16:46:16.524+0200"
    ],
    "refNo_digit": [],
    "colour": [],
    "wordingOfConditions": [],
    "inciUsaName": [],
    "relatedRegulations": [],
    "perfuming": [
      "N"
    ],
    "status": []
  },
  "enrichedMetadata": {},
  "children": [],
  "highlightedFragments": []
}