{
  "apiVersion": "2.145.3",
  "reference": "40e1fac0-ee43-40a0-85d4-e6c4743614b6",
  "url": "urn:test",
  "title": null,
  "contentType": "text/plain",
  "language": "en",
  "databaseLabel": "Growth Cosmetic Ingredients and Substances",
  "database": "GROWTH_COSING",
  "summary": "",
  "weight": 17.585997,
  "groupById": null,
  "content": "",
  "accessRestriction": false,
  "pages": null,
  "checksum": "E3B0C44298FC1C149AFBF4C8996FB92427AE41E4649B934CA495991B7852B855",
  "metadata": {
    "nameOfCommonIngredientsGlossary": [
      "TEA-PEG-50 HYDROGENATED CASTOR OIL SUCCINATE"
    ],
    "otherRestrictions": [
      "ban substances that deplete the ozone layer"
    ],
    "note": [],
    "refNo": [],
    "sccsOpinionUrls": [],
    "innName": [],
    "other": [],
    "itemType": [
      "ingredient"
    ],
    "chemicalName": [],
    "sccsOpinion": [],
    "refNo_letter": [],
    "language": [
      "en"
    ],
    "chemicalDescription": [
      "TEA-PEG-50 Hydrogenated Castor Oil Succinate is the triethanalomine salt of PEG-50 hydrogenated castor oil succinate (q.v.)"
    ],
    "esST_checksum": [
      "E3B0C44298FC1C149AFBF4C8996FB92427AE41E4649B934CA495991B7852B855"
    ],
    "reference": [
      "F461D6C0EE4310CDC2DF96B9EEBC45F6"
    ],
    "cosmeticRestriction": [
      "III/62"
    ],
    "ecNo": [],
    "maximumConcentration": [],
    "identifiedIngredient": [
      "28313"
    ],
    "officialJournalPublication": [
      "Y"
    ],
    "inciName": [
      "TEA-PEG-50 HYDROGENATED CASTOR OIL SUCCINATE"
    ],
    "esST_FileName": [
      "file.txt"
    ],
    "casNo": [],
    "substanceId": [
      "60172"
    ],
    "DATASOURCE": [
      "GROWTH_COSING"
    ],
    "annexNo": [],
    "productTypeBodyParts": [],
    "phEurName": [],
    "es_ContentType": [
      "text/plain"
    ],
    "otherRegulations": [],
    "classificationInformation": [
      "[]"
    ],
    "functionName": [
      "SURFACTANT - EMULSIFYING"
    ],
    "esDA_IngestDate": [
      "2023-05-22T14:58:31.987+0200"
    ],
    "currentVersion": [
      "1"
    ],
    "corporate-search-version": [
      "102"
    ],
    "url": [
      "urn:test"
    ],
    "esST_URL": [
      "urn:test"
    ],
    "esDA_QueueDate": [
      "2023-05-22T14:58:31.957+0200"
    ],
    "refNo_digit": [],
    "colour": [],
    "datasource": [
      "GROWTH_COSING"
    ],
    "wordingOfConditions": [],
    "inciUsaName": [],
    "relatedRegulations": [],
    "perfuming": [
      "N"
    ],
    "status": [
      "Active"
    ]
  },
  "enrichedMetadata": {},
  "children": [],
  "highlightedFragments": []
}