{
  "apiVersion": "2.146",
  "reference": "45eb79ba-1bcf-44d4-b00d-401500c709e2",
  "url": "urn:test",
  "title": null,
  "contentType": "text/plain",
  "language": "en",
  "databaseLabel": "Growth Cosmetic Ingredients and Substances",
  "database": "GROWTH_COSING",
  "summary": "",
  "weight": 12.088693,
  "groupById": null,
  "content": "",
  "accessRestriction": false,
  "pages": null,
  "checksum": "E3B0C44298FC1C149AFBF4C8996FB92427AE41E4649B934CA495991B7852B855",
  "metadata": {
    "nameOfCommonIngredientsGlossary": [
      "CURCUMA LONGA ROOT POWDER"
    ],
    "otherRestrictions": [],
    "note": [],
    "refNo": [],
    "sccsOpinionUrls": [],
    "innName": [],
    "other": [],
    "itemType": [
      "ingredient"
    ],
    "chemicalName": [],
    "sccsOpinion": [],
    "refNo_letter": [],
    "language": [
      "en"
    ],
    "chemicalDescription": [
      "Curcuma Longa (Turmeric) Root Powder is a powder obtained from the dried, ground rhizomes of Curcuma longa, Zingiberaceae."
    ],
    "esST_checksum": [
      "E3B0C44298FC1C149AFBF4C8996FB92427AE41E4649B934CA495991B7852B855"
    ],
    "reference": [
      "40F9BB4B0B909EF3B90AFAF980EFCEE6"
    ],
    "cosmeticRestriction": [],
    "ecNo": [
      "283-882-1"
    ],
    "maximumConcentration": [],
    "identifiedIngredient": [],
    "officialJournalPublication": [
      "Y"
    ],
    "inciName": [
      "CURCUMA LONGA ROOT POWDER"
    ],
    "esST_FileName": [
      "file.txt"
    ],
    "casNo": [
      "84775-52-0"
    ],
    "substanceId": [
      "91077"
    ],
    "DATASOURCE": [
      "GROWTH_COSING"
    ],
    "annexNo": [],
    "productTypeBodyParts": [],
    "phEurName": [],
    "es_ContentType": [
      "text/plain"
    ],
    "otherRegulations": [],
    "classificationInformation": [
      "[]"
    ],
    "functionName": [
      "SKIN CONDITIONING"
    ],
    "esDA_IngestDate": [
      "2023-05-22T16:37:58.290+0200"
    ],
    "currentVersion": [
      "1"
    ],
    "corporate-search-version": [
      "102"
    ],
    "url": [
      "urn:test"
    ],
    "esST_URL": [
      "urn:test"
    ],
    "esDA_QueueDate": [
      "2023-05-22T16:37:58.257+0200"
    ],
    "refNo_digit": [],
    "colour": [],
    "datasource": [
      "GROWTH_COSING"
    ],
    "wordingOfConditions": [],
    "inciUsaName": [],
    "relatedRegulations": [],
    "perfuming": [
      "N"
    ],
    "status": [
      "Active"
    ]
  },
  "enrichedMetadata": {},
  "children": [],
  "highlightedFragments": [],
  "citation": "45eb79ba-1bcf-44d4-b00d-401500c709e2. Available at: urn:test",
  "score": 12.088693
}