{
  "apiVersion": "2.145.3",
  "reference": "52bee4ea-330b-4901-89d2-5b0efe461a77",
  "url": "urn:test",
  "title": null,
  "contentType": "text/plain",
  "language": "en",
  "databaseLabel": "Growth Cosmetic Ingredients and Substances",
  "database": "GROWTH_COSING",
  "summary": "",
  "weight": 25.06698,
  "groupById": null,
  "content": "",
  "accessRestriction": false,
  "pages": null,
  "checksum": "E3B0C44298FC1C149AFBF4C8996FB92427AE41E4649B934CA495991B7852B855",
  "metadata": {
    "nameOfCommonIngredientsGlossary": [
      "CHONDRUS CRISPUS"
    ],
    "otherRestrictions": [],
    "note": [],
    "refNo": [],
    "sccsOpinionUrls": [],
    "innName": [],
    "other": [],
    "itemType": [
      "ingredient"
    ],
    "chemicalName": [
      "Irish Moss"
    ],
    "sccsOpinion": [],
    "refNo_letter": [],
    "language": [
      "en"
    ],
    "chemicalDescription": [
      "Chondrus Crispus is the material obtained from the whole alga, Chondrus crispus, Gigartinacea."
    ],
    "esST_checksum": [
      "E3B0C44298FC1C149AFBF4C8996FB92427AE41E4649B934CA495991B7852B855"
    ],
    "reference": [
      "96B5D5950D995128C3580BC9561902B9"
    ],
    "cosmeticRestriction": [],
    "ecNo": [],
    "maximumConcentration": [],
    "identifiedIngredient": [],
    "officialJournalPublication": [
      "Y"
    ],
    "inciName": [
      "CHONDRUS CRISPUS"
    ],
    "esST_FileName": [
      "file.txt"
    ],
    "casNo": [],
    "substanceId": [
      "90042"
    ],
    "DATASOURCE": [
      "GROWTH_COSING"
    ],
    "annexNo": [],
    "productTypeBodyParts": [],
    "phEurName": [],
    "es_ContentType": [
      "text/plain"
    ],
    "otherRegulations": [],
    "classificationInformation": [
      "[]"
    ],
    "functionName": [
      "FRAGRANCE",
      "SKIN CONDITIONING"
    ],
    "esDA_IngestDate": [
      "2023-05-22T16:32:57.159+0200"
    ],
    "currentVersion": [],
    "corporate-search-version": [
      "102"
    ],
    "url": [
      "urn:test"
    ],
    "esST_URL": [
      "urn:test"
    ],
    "esDA_QueueDate": [
      "2023-05-22T16:32:57.134+0200"
    ],
    "refNo_digit": [],
    "colour": [],
    "datasource": [
      "GROWTH_COSING"
    ],
    "wordingOfConditions": [],
    "inciUsaName": [],
    "relatedRegulations": [],
    "perfuming": [
      "N"
    ],
    "status": [
      "Active"
    ]
  },
  "enrichedMetadata": {},
  "children": [],
  "highlightedFragments": []
}