{
  "apiVersion": "2.145.3",
  "reference": "8fde100c-845a-47f5-9b9b-8d5242a5d8c5",
  "url": "urn:test",
  "title": null,
  "contentType": "text/plain",
  "language": "en",
  "databaseLabel": "Growth Cosmetic Ingredients and Substances",
  "database": "GROWTH_COSING",
  "summary": "",
  "weight": 16.399397,
  "groupById": null,
  "content": "",
  "accessRestriction": false,
  "pages": null,
  "checksum": "E3B0C44298FC1C149AFBF4C8996FB92427AE41E4649B934CA495991B7852B855",
  "metadata": {
    "nameOfCommonIngredientsGlossary": [
      "SODIUM TALLOWATE"
    ],
    "otherRestrictions": [],
    "note": [],
    "refNo": [],
    "sccsOpinionUrls": [],
    "innName": [],
    "other": [],
    "itemType": [
      "ingredient"
    ],
    "chemicalName": [],
    "sccsOpinion": [],
    "refNo_letter": [],
    "language": [
      "en"
    ],
    "chemicalDescription": [
      "Fatty acids, tallow, sodium salts"
    ],
    "esST_checksum": [
      "E3B0C44298FC1C149AFBF4C8996FB92427AE41E4649B934CA495991B7852B855"
    ],
    "reference": [
      "F8E276B4A88E2392CDF6BAF5BE06ABF6"
    ],
    "cosmeticRestriction": [],
    "ecNo": [
      "232-491-4"
    ],
    "maximumConcentration": [],
    "identifiedIngredient": [],
    "officialJournalPublication": [
      "Y"
    ],
    "inciName": [
      "SODIUM TALLOWATE"
    ],
    "esST_FileName": [
      "file.txt"
    ],
    "casNo": [
      "8052-48-0"
    ],
    "substanceId": [
      "80216"
    ],
    "DATASOURCE": [
      "GROWTH_COSING"
    ],
    "annexNo": [],
    "productTypeBodyParts": [],
    "phEurName": [],
    "es_ContentType": [
      "text/plain"
    ],
    "otherRegulations": [],
    "classificationInformation": [
      "[]"
    ],
    "functionName": [
      "CLEANSING",
      "SURFACTANT - EMULSIFYING",
      "SURFACTANT - FOAM BOOSTING",
      "SURFACTANT - CLEANSING",
      "VISCOSITY CONTROLLING"
    ],
    "esDA_IngestDate": [
      "2023-05-22T14:24:53.408+0200"
    ],
    "currentVersion": [
      "1"
    ],
    "corporate-search-version": [
      "102"
    ],
    "url": [
      "urn:test"
    ],
    "esST_URL": [
      "urn:test"
    ],
    "esDA_QueueDate": [
      "2023-05-22T14:24:53.381+0200"
    ],
    "refNo_digit": [],
    "colour": [],
    "datasource": [
      "GROWTH_COSING"
    ],
    "wordingOfConditions": [],
    "inciUsaName": [],
    "relatedRegulations": [],
    "perfuming": [
      "N"
    ],
    "status": [
      "Active"
    ]
  },
  "enrichedMetadata": {},
  "children": [],
  "highlightedFragments": []
}