{
  "apiVersion": "2.145.3",
  "reference": "bfb6279b-2ca4-4579-b48b-6fdba77a041c",
  "url": "urn:test",
  "title": null,
  "contentType": "text/plain",
  "language": "en",
  "databaseLabel": "Growth Cosmetic Ingredients and Substances",
  "database": "GROWTH_COSING",
  "summary": "",
  "weight": 8.695683,
  "groupById": null,
  "content": "",
  "accessRestriction": false,
  "pages": null,
  "checksum": "E3B0C44298FC1C149AFBF4C8996FB92427AE41E4649B934CA495991B7852B855",
  "metadata": {
    "nameOfCommonIngredientsGlossary": [
      "CI 15510"
    ],
    "otherRestrictions": [],
    "note": [],
    "refNo": [],
    "sccsOpinionUrls": [
      "http://ec.europa.eu/health/ph_risk/committees/sccp/documents/out259_en.pdf",
      "http://ec.europa.eu/health/scientific_committees/consumer_safety/docs/sccs_o_057.pdf",
      "http://ec.europa.eu/health/scientific_committees/consumer_safety/docs/sccs_o_158.pdf"
    ],
    "innName": [],
    "other": [],
    "itemType": [
      "ingredient"
    ],
    "chemicalName": [
      "Sodium 4-[(2-hydroxy-1-naphthyl)azo]benzenesulphonate"
    ],
    "sccsOpinion": [
      "Opinion on Acid Orange 7",
      "Opinion on Acid Orange 7",
      "Opinion on Acid Orange 7"
    ],
    "refNo_letter": [],
    "language": [
      "en"
    ],
    "chemicalDescription": [
      "CI 15510 is classed chemically as a monoazo colour. It conforms to the formula:"
    ],
    "esST_checksum": [
      "E3B0C44298FC1C149AFBF4C8996FB92427AE41E4649B934CA495991B7852B855"
    ],
    "reference": [
      "0D9E39A504E4841777077CAC0E069F92"
    ],
    "cosmeticRestriction": [
      "IV/21"
    ],
    "ecNo": [
      "211-199-0"
    ],
    "maximumConcentration": [],
    "identifiedIngredient": [
      "30408"
    ],
    "officialJournalPublication": [
      "Y"
    ],
    "inciName": [
      "CI 15510"
    ],
    "esST_FileName": [
      "file.txt"
    ],
    "casNo": [
      "633-96-5"
    ],
    "substanceId": [
      "32714"
    ],
    "DATASOURCE": [
      "GROWTH_COSING"
    ],
    "annexNo": [],
    "productTypeBodyParts": [],
    "phEurName": [],
    "es_ContentType": [
      "text/plain"
    ],
    "otherRegulations": [],
    "classificationInformation": [
      "[]"
    ],
    "functionName": [
      "COLORANT"
    ],
    "esDA_IngestDate": [
      "2023-05-22T13:08:21.354+0200"
    ],
    "currentVersion": [
      "1"
    ],
    "corporate-search-version": [
      "102"
    ],
    "url": [
      "urn:test"
    ],
    "esST_URL": [
      "urn:test"
    ],
    "esDA_QueueDate": [
      "2023-05-22T13:08:21.320+0200"
    ],
    "refNo_digit": [],
    "colour": [],
    "datasource": [
      "GROWTH_COSING"
    ],
    "wordingOfConditions": [],
    "inciUsaName": [],
    "relatedRegulations": [],
    "perfuming": [
      "N"
    ],
    "status": [
      "Active"
    ]
  },
  "enrichedMetadata": {},
  "children": [],
  "highlightedFragments": []
}