{
  "apiVersion": "2.146",
  "reference": "c0bc607d-6d57-4cb3-be6c-86fbafe5375a",
  "url": "urn:test",
  "title": null,
  "contentType": "text/plain",
  "language": "en",
  "databaseLabel": "Growth Cosmetic Ingredients and Substances",
  "database": "GROWTH_COSING",
  "summary": "",
  "weight": 12.088693,
  "groupById": null,
  "content": "",
  "accessRestriction": false,
  "pages": null,
  "checksum": "E3B0C44298FC1C149AFBF4C8996FB92427AE41E4649B934CA495991B7852B855",
  "metadata": {
    "nameOfCommonIngredientsGlossary": [
      "FUSCOPORIA OBLIQUA CULTURE FILTRATE"
    ],
    "otherRestrictions": [
      "ban substances that deplete the ozone layer",
      "ban substances that deplete the ozone layer"
    ],
    "note": [],
    "refNo": [],
    "sccsOpinionUrls": [],
    "innName": [],
    "other": [],
    "itemType": [
      "ingredient"
    ],
    "chemicalName": [],
    "sccsOpinion": [],
    "refNo_letter": [],
    "language": [
      "en"
    ],
    "chemicalDescription": [
      "Fuscoporia Obliqua Culture Filtrate is a filtrate of a culture of the Mushroom, Fuscoporia obliqua"
    ],
    "esST_checksum": [
      "E3B0C44298FC1C149AFBF4C8996FB92427AE41E4649B934CA495991B7852B855"
    ],
    "reference": [
      "35AF28E2F378E913FBE3F5C5D78E3657"
    ],
    "cosmeticRestriction": [],
    "ecNo": [
      "-"
    ],
    "maximumConcentration": [],
    "identifiedIngredient": [],
    "officialJournalPublication": [
      "Y"
    ],
    "inciName": [
      "FUSCOPORIA OBLIQUA CULTURE FILTRATE"
    ],
    "esST_FileName": [
      "file.txt"
    ],
    "casNo": [
      "-"
    ],
    "substanceId": [
      "82648"
    ],
    "DATASOURCE": [
      "GROWTH_COSING"
    ],
    "annexNo": [],
    "productTypeBodyParts": [],
    "phEurName": [],
    "es_ContentType": [
      "text/plain"
    ],
    "otherRegulations": [],
    "classificationInformation": [
      "[]"
    ],
    "functionName": [
      "SKIN CONDITIONING"
    ],
    "esDA_IngestDate": [
      "2023-05-22T15:11:06.388+0200"
    ],
    "currentVersion": [
      "1"
    ],
    "corporate-search-version": [
      "102"
    ],
    "url": [
      "urn:test"
    ],
    "esST_URL": [
      "urn:test"
    ],
    "esDA_QueueDate": [
      "2023-05-22T15:11:06.355+0200"
    ],
    "refNo_digit": [],
    "colour": [],
    "datasource": [
      "GROWTH_COSING"
    ],
    "wordingOfConditions": [],
    "inciUsaName": [
      "FUSCOPORIA OBLIQUA (MUSHROOM) CULTURE FILTRATE"
    ],
    "relatedRegulations": [],
    "perfuming": [
      "N"
    ],
    "status": [
      "Active"
    ]
  },
  "enrichedMetadata": {},
  "children": [],
  "highlightedFragments": [],
  "citation": "c0bc607d-6d57-4cb3-be6c-86fbafe5375a. Available at: urn:test",
  "score": 12.088693
}