{
  "apiVersion": "2.145.3",
  "reference": "d8adb3dc-c265-48e4-a22c-20f4c6ae8b82",
  "url": "urn:test",
  "title": null,
  "contentType": "text/plain",
  "language": "en",
  "databaseLabel": "Growth Cosmetic Ingredients and Substances",
  "database": "GROWTH_COSING",
  "summary": "",
  "weight": 9.974256,
  "groupById": null,
  "content": "",
  "accessRestriction": false,
  "pages": null,
  "checksum": "E3B0C44298FC1C149AFBF4C8996FB92427AE41E4649B934CA495991B7852B855",
  "metadata": {
    "nameOfCommonIngredientsGlossary": [
      "ELAEIS OLEIFERA FRUIT OIL"
    ],
    "otherRestrictions": [],
    "note": [],
    "refNo": [],
    "sccsOpinionUrls": [],
    "innName": [],
    "other": [],
    "itemType": [
      "ingredient"
    ],
    "chemicalName": [],
    "sccsOpinion": [],
    "refNo_letter": [],
    "language": [
      "en"
    ],
    "chemicalDescription": [
      "Elaeis Oleifera Fruit Oil is the oil expressed from the fruit of Elaeis oleifera, plant formed by the hybridization of the Palm, Elaeis guineensis with Elaeis oleifera"
    ],
    "esST_checksum": [
      "E3B0C44298FC1C149AFBF4C8996FB92427AE41E4649B934CA495991B7852B855"
    ],
    "reference": [
      "669B3EF9CA793C1116F496D80F144AF8"
    ],
    "cosmeticRestriction": [],
    "ecNo": [
      "232-316-1"
    ],
    "maximumConcentration": [],
    "identifiedIngredient": [],
    "officialJournalPublication": [
      "Y"
    ],
    "inciName": [
      "ELAEIS OLEIFERA FRUIT OIL"
    ],
    "esST_FileName": [
      "file.txt"
    ],
    "casNo": [
      "8002-75-3"
    ],
    "substanceId": [
      "88966"
    ],
    "DATASOURCE": [
      "GROWTH_COSING"
    ],
    "annexNo": [],
    "productTypeBodyParts": [],
    "phEurName": [],
    "es_ContentType": [
      "text/plain"
    ],
    "otherRegulations": [],
    "classificationInformation": [
      "[]"
    ],
    "functionName": [
      "SKIN CONDITIONING - EMOLLIENT",
      "HAIR CONDITIONING",
      "SKIN CONDITIONING"
    ],
    "esDA_IngestDate": [
      "2023-05-22T15:46:45.036+0200"
    ],
    "currentVersion": [
      "1"
    ],
    "corporate-search-version": [
      "102"
    ],
    "url": [
      "urn:test"
    ],
    "esST_URL": [
      "urn:test"
    ],
    "esDA_QueueDate": [
      "2023-05-22T15:46:44.989+0200"
    ],
    "refNo_digit": [],
    "colour": [],
    "datasource": [
      "GROWTH_COSING"
    ],
    "wordingOfConditions": [],
    "inciUsaName": [],
    "relatedRegulations": [],
    "perfuming": [
      "N"
    ],
    "status": [
      "Active"
    ]
  },
  "enrichedMetadata": {},
  "children": [],
  "highlightedFragments": []
}