{
  "apiVersion": "2.145.3",
  "reference": "f03a618c-4404-4172-9b44-2e3ff81abe6f",
  "url": "urn:test",
  "title": null,
  "contentType": "text/plain",
  "language": "en",
  "databaseLabel": "Growth Cosmetic Ingredients and Substances",
  "database": "GROWTH_COSING",
  "summary": "",
  "weight": 13.808177,
  "groupById": null,
  "content": "",
  "accessRestriction": false,
  "pages": null,
  "checksum": "E3B0C44298FC1C149AFBF4C8996FB92427AE41E4649B934CA495991B7852B855",
  "metadata": {
    "nameOfCommonIngredientsGlossary": [
      "PRUNUS AMYGDALUS DULCIS SHELL POWDER"
    ],
    "otherRestrictions": [
      "ban substances that deplete the ozone layer"
    ],
    "note": [],
    "refNo": [],
    "sccsOpinionUrls": [],
    "innName": [],
    "other": [],
    "itemType": [
      "ingredient"
    ],
    "chemicalName": [],
    "sccsOpinion": [],
    "refNo_letter": [],
    "language": [
      "en"
    ],
    "chemicalDescription": [
      "Prunus Amygdalus Dulcis Shell Powder is a powder obtained from the dried, ground shell of the Sweet Almond Tree, Prunus amygdalus var. dulcis, Rosaceae"
    ],
    "esST_checksum": [
      "E3B0C44298FC1C149AFBF4C8996FB92427AE41E4649B934CA495991B7852B855"
    ],
    "reference": [
      "84179D7EEDCE272E46D670A802D84C01"
    ],
    "cosmeticRestriction": [],
    "ecNo": [
      "291-063-5"
    ],
    "maximumConcentration": [],
    "identifiedIngredient": [],
    "officialJournalPublication": [
      "Y"
    ],
    "inciName": [
      "PRUNUS AMYGDALUS DULCIS SHELL POWDER"
    ],
    "esST_FileName": [
      "file.txt"
    ],
    "casNo": [
      "90320-37-9"
    ],
    "substanceId": [
      "58571"
    ],
    "DATASOURCE": [
      "GROWTH_COSING"
    ],
    "annexNo": [],
    "productTypeBodyParts": [],
    "phEurName": [],
    "es_ContentType": [
      "text/plain"
    ],
    "otherRegulations": [],
    "classificationInformation": [
      "[]"
    ],
    "functionName": [
      "ABRASIVE"
    ],
    "esDA_IngestDate": [
      "2023-05-22T14:41:28.940+0200"
    ],
    "currentVersion": [
      "1"
    ],
    "corporate-search-version": [
      "102"
    ],
    "url": [
      "urn:test"
    ],
    "esST_URL": [
      "urn:test"
    ],
    "esDA_QueueDate": [
      "2023-05-22T14:41:28.915+0200"
    ],
    "refNo_digit": [],
    "colour": [],
    "datasource": [
      "GROWTH_COSING"
    ],
    "wordingOfConditions": [],
    "inciUsaName": [
      "PRUNUS AMYGDALUS DULCIS (SWEET ALMOND) SHELL POWDER"
    ],
    "relatedRegulations": [],
    "perfuming": [
      "N"
    ],
    "status": [
      "Active"
    ]
  },
  "enrichedMetadata": {},
  "children": [],
  "highlightedFragments": []
}