{
  "apiVersion": "2.145.3",
  "reference": "f20c44c0-64fe-4099-82e8-8dc81bef843d",
  "url": "urn:test",
  "title": null,
  "contentType": "text/plain",
  "language": "en",
  "databaseLabel": "Growth Cosmetic Ingredients and Substances",
  "database": "GROWTH_COSING",
  "summary": "",
  "weight": 15.811466,
  "groupById": null,
  "content": "",
  "accessRestriction": false,
  "pages": null,
  "checksum": "E3B0C44298FC1C149AFBF4C8996FB92427AE41E4649B934CA495991B7852B855",
  "metadata": {
    "nameOfCommonIngredientsGlossary": [
      "Atractylodes Japonica Rhizome/(Achyranthes Bidentata/Anemarrhena Asphodeloides/Cynanchum Wilfordii/Pinellia Ternata/Platycodon Grandiflorus/Polygonum Multiflorum/Scutellaria Baicalensis) Root/Acorus Gramineus Root/Stem/Peucedanum Japonicum Extract"
    ],
    "otherRestrictions": [],
    "note": [],
    "refNo": [],
    "sccsOpinionUrls": [],
    "innName": [],
    "other": [],
    "itemType": [
      "ingredient"
    ],
    "chemicalName": [],
    "sccsOpinion": [],
    "refNo_letter": [],
    "language": [
      "en"
    ],
    "chemicalDescription": [
      "This is the extract of the rhizomes of Atractyloides japonica ; the roots of Anemarrhena asphodeloides , Cynanchum wilfordii , Pinellia ternata , Platycodon grandiflorum , Polygonum multiflorum , and Scutellaria baicalensis ; the roots and stems of Acorus gramineus and the whole plant, Peucedanum japonicum."
    ],
    "esST_checksum": [
      "E3B0C44298FC1C149AFBF4C8996FB92427AE41E4649B934CA495991B7852B855"
    ],
    "reference": [
      "A10BECF70E7BF3D6BCA3A6A96CFCBAE4"
    ],
    "cosmeticRestriction": [],
    "ecNo": [],
    "maximumConcentration": [],
    "identifiedIngredient": [],
    "officialJournalPublication": [
      "Y"
    ],
    "inciName": [
      "ATRACTYLODES JAPONICA RHIZOME/(ACHYRANTHES BIDENTATA/ANEMARRHENA ASPHODELOIDES/CYNANCHUM WILFORDII/PINELLIA TERNATA/PLATYCODON GRANDIFLORUS/POLYGONUM MULTIFLORUM/SCUTELLARIA BAICALENSIS) ROOT/ACORUS GRAMINEUS ROOT/STEM/PEUCEDANUM JAPONICUM EXTRACT"
    ],
    "esST_FileName": [
      "file.txt"
    ],
    "casNo": [],
    "substanceId": [
      "92165"
    ],
    "DATASOURCE": [
      "GROWTH_COSING"
    ],
    "annexNo": [],
    "productTypeBodyParts": [],
    "phEurName": [],
    "es_ContentType": [
      "text/plain"
    ],
    "otherRegulations": [],
    "classificationInformation": [
      "[]"
    ],
    "functionName": [
      "SKIN CONDITIONING"
    ],
    "esDA_IngestDate": [
      "2023-05-22T16:42:25.017+0200"
    ],
    "currentVersion": [],
    "corporate-search-version": [
      "102"
    ],
    "url": [
      "urn:test"
    ],
    "esST_URL": [
      "urn:test"
    ],
    "esDA_QueueDate": [
      "2023-05-22T16:42:24.988+0200"
    ],
    "refNo_digit": [],
    "colour": [],
    "datasource": [
      "GROWTH_COSING"
    ],
    "wordingOfConditions": [],
    "inciUsaName": [],
    "relatedRegulations": [],
    "perfuming": [
      "N"
    ],
    "status": [
      "Active"
    ]
  },
  "enrichedMetadata": {},
  "children": [],
  "highlightedFragments": []
}