{
  "apiVersion": "2.145.3",
  "reference": "f9c1c86d-4521-4621-a8b3-879216508613",
  "url": "urn:test",
  "title": null,
  "contentType": "text/plain",
  "language": "en",
  "databaseLabel": "Growth Cosmetic Ingredients and Substances",
  "database": "GROWTH_COSING",
  "summary": "",
  "weight": 7.769473,
  "groupById": null,
  "content": "",
  "accessRestriction": false,
  "pages": null,
  "checksum": "E3B0C44298FC1C149AFBF4C8996FB92427AE41E4649B934CA495991B7852B855",
  "metadata": {
    "nameOfCommonIngredientsGlossary": [
      "AMMONIUM CHLORIDE"
    ],
    "otherRestrictions": [
      "ban substances that deplete the ozone layer"
    ],
    "note": [],
    "refNo": [],
    "sccsOpinionUrls": [],
    "innName": [
      "ammonium chloride"
    ],
    "other": [],
    "itemType": [
      "ingredient"
    ],
    "chemicalName": [
      "Ammonium chloride"
    ],
    "sccsOpinion": [],
    "refNo_letter": [],
    "language": [
      "en"
    ],
    "chemicalDescription": [],
    "esST_checksum": [
      "E3B0C44298FC1C149AFBF4C8996FB92427AE41E4649B934CA495991B7852B855"
    ],
    "reference": [
      "EF0494C5F8CD320176EEDAC215E4AB57"
    ],
    "cosmeticRestriction": [],
    "ecNo": [
      "235-186-4"
    ],
    "maximumConcentration": [],
    "identifiedIngredient": [],
    "officialJournalPublication": [
      "Y"
    ],
    "inciName": [
      "AMMONIUM CHLORIDE"
    ],
    "esST_FileName": [
      "file.txt"
    ],
    "casNo": [
      "12125-02-9"
    ],
    "substanceId": [
      "31857"
    ],
    "DATASOURCE": [
      "GROWTH_COSING"
    ],
    "annexNo": [],
    "productTypeBodyParts": [],
    "phEurName": [
      "ammonii chloridum"
    ],
    "es_ContentType": [
      "text/plain"
    ],
    "otherRegulations": [],
    "classificationInformation": [
      "[]"
    ],
    "functionName": [
      "BUFFERING",
      "FRAGRANCE",
      "VISCOSITY CONTROLLING"
    ],
    "esDA_IngestDate": [
      "2023-05-22T15:03:33.102+0200"
    ],
    "currentVersion": [
      "1"
    ],
    "corporate-search-version": [
      "102"
    ],
    "url": [
      "urn:test"
    ],
    "esST_URL": [
      "urn:test"
    ],
    "esDA_QueueDate": [
      "2023-05-22T15:03:33.080+0200"
    ],
    "refNo_digit": [],
    "colour": [],
    "datasource": [
      "GROWTH_COSING"
    ],
    "wordingOfConditions": [],
    "inciUsaName": [],
    "relatedRegulations": [],
    "perfuming": [
      "N"
    ],
    "status": [
      "Active"
    ]
  },
  "enrichedMetadata": {},
  "children": [],
  "highlightedFragments": []
}