{
  "apiVersion": "2.146",
  "reference": "1736c420-e920-4bc3-a91b-2d3b2d0fe4e5",
  "url": "urn:test",
  "title": null,
  "contentType": "text/plain",
  "language": "en",
  "databaseLabel": "Growth Cosmetic Ingredients and Substances",
  "database": "GROWTH_COSING",
  "summary": "",
  "weight": 12.336397,
  "groupById": null,
  "content": "",
  "accessRestriction": false,
  "pages": null,
  "checksum": "E3B0C44298FC1C149AFBF4C8996FB92427AE41E4649B934CA495991B7852B855",
  "metadata": {
    "nameOfCommonIngredientsGlossary": [
      "CHENOPODIUM QUINOA SEED OIL"
    ],
    "otherRestrictions": [
      "ban substances that deplete the ozone layer"
    ],
    "note": [],
    "refNo": [],
    "sccsOpinionUrls": [],
    "innName": [],
    "other": [],
    "itemType": [
      "ingredient"
    ],
    "chemicalName": [],
    "sccsOpinion": [],
    "refNo_letter": [],
    "language": [
      "en"
    ],
    "chemicalDescription": [
      "Chenopodium Quinoa Seed Oil is the oil expressed from seeds of Chenopodium quinoa, Chenopodiaceae"
    ],
    "esST_checksum": [
      "E3B0C44298FC1C149AFBF4C8996FB92427AE41E4649B934CA495991B7852B855"
    ],
    "reference": [
      "9107AD55BBBA8B06F4A93ECEF90B437B"
    ],
    "cosmeticRestriction": [],
    "ecNo": [
      "-"
    ],
    "maximumConcentration": [],
    "identifiedIngredient": [],
    "officialJournalPublication": [
      "Y"
    ],
    "inciName": [
      "CHENOPODIUM QUINOA SEED OIL"
    ],
    "esST_FileName": [
      "file.txt"
    ],
    "casNo": [
      "225234-01-5"
    ],
    "substanceId": [
      "55304"
    ],
    "DATASOURCE": [
      "GROWTH_COSING"
    ],
    "annexNo": [],
    "productTypeBodyParts": [],
    "phEurName": [],
    "es_ContentType": [
      "text/plain"
    ],
    "otherRegulations": [],
    "classificationInformation": [
      "[]"
    ],
    "functionName": [
      "SKIN CONDITIONING - EMOLLIENT",
      "SKIN CONDITIONING"
    ],
    "esDA_IngestDate": [
      "2023-05-22T14:34:47.451+0200"
    ],
    "currentVersion": [
      "1"
    ],
    "corporate-search-version": [
      "102"
    ],
    "url": [
      "urn:test"
    ],
    "esST_URL": [
      "urn:test"
    ],
    "esDA_QueueDate": [
      "2023-05-22T14:34:47.378+0200"
    ],
    "refNo_digit": [],
    "colour": [],
    "datasource": [
      "GROWTH_COSING"
    ],
    "wordingOfConditions": [],
    "inciUsaName": [],
    "relatedRegulations": [],
    "perfuming": [
      "N"
    ],
    "status": [
      "Active"
    ]
  },
  "enrichedMetadata": {},
  "children": [],
  "highlightedFragments": [],
  "citation": "1736c420-e920-4bc3-a91b-2d3b2d0fe4e5. Available at: urn:test",
  "score": 12.336397
}