{
  "product_information": {
    "product_url": "https://www.etos.nl/producten/john-frieda-violet-crush-purple-toning-mask-250-ml-120600140.html",
    "images": [
      "https://www.etos.nl/dw/image/v2/BCTN_PRD/on/demandware.static/-/Sites-etos-master-catalog/default/dw3f9c2de4/images/120600140/120600140_c0cc782e-1196-4b07-b991-c816e5332f24.jpg?sw=800&sfrm=png&q=75",
      "https://www.etos.nl/dw/image/v2/BCTN_PRD/on/demandware.static/-/Sites-etos-master-catalog/default/dw2e79a1d8/images/120600140/120600140_cfd93e76-f134-4d3e-a16b-90576fe27e87.jpg?sw=800&sfrm=png&q=75",
      "https://www.etos.nl/dw/image/v2/BCTN_PRD/on/demandware.static/-/Sites-etos-master-catalog/default/dwed46a2c6/images/120600140/120600140_6329d28f-bc2a-473f-bbc8-e22bdc6a998c.jpg?sw=800&sfrm=png&q=75",
      "https://www.etos.nl/dw/image/v2/BCTN_PRD/on/demandware.static/-/Sites-etos-master-catalog/default/dw83908e5d/images/120600140/120600140_9abde919-0065-4466-a95c-71d2f6f94dba.jpg?sw=800&sfrm=png&q=75",
      "https://www.etos.nl/dw/image/v2/BCTN_PRD/on/demandware.static/-/Sites-etos-master-catalog/default/dwcb858488/images/120600140/120600140_119359a3-335a-4732-b137-e639ba9cfa9c.jpg?sw=800&sfrm=png&q=75",
      "https://www.etos.nl/dw/image/v2/BCTN_PRD/on/demandware.static/-/Sites-etos-master-catalog/default/dw59706a83/images/120600140/120600140_8fcda3db-171d-4e2c-b6fe-00062f26c3cf.jpg?sw=800&sfrm=png&q=75"
    ],
    "website": "www.etos.nl",
    "product_name": "John Frieda Violet Crush Purple Toning Mask 250 ML",
    "price": null,
    "description": "Het product\nHet John Frieda Violet Crush Purple Toning Mask is een   intensieve verzorging die ongewenste warme tinten in blond haar direct   neutraliseert. De krachtige formule versterkt het haar, helpt haarbreuk te   verminderen en geeft je blonde lokken een koele, stralende finish. Voor een   salonfris resultaat en een gezond, veerkrachtig gevoel.\nKenmerken\n•\tSamengesteld   zonder siliconen.     •\tVegan formule, vrij van dierlijke ingrediënten.     •\tVeilig voor gebruik op gekleurd en natuurlijk haar.     •\tMet gemalen Violet pigmenten en Provitamine B5.     •\tGeschikt voor blond haar.     •\tVerpakking\ngemaakt van 45% gerecycled materiaal (\nalleen de container).\nHoe werkt het?\nNa   gebruik van de Violet Crush Shampoo, royaal en gelijkmatig aanbrengen op nat   haar en doorkammen. Gedurende 1-3 minuten en niet langer dan 5 minuten laten   inwerken en vervolgens goed uitspoelen. Handen onmiddellijk wassen. Wekelijks   of naar behoefte gebruiken tot het gewenste kleurresultaat is bereikt.\nGebruik\nNa   gebruik van de Violet Crush Shampoo, royaal en gelijkmatig aanbrengen op nat   haar en doorkammen. Gedurende 1-3 minuten en niet langer dan 5 minuten laten   inwerken en vervolgens goed uitspoelen. Handen onmiddellijk wassen. Wekelijks   of naar behoefte gebruiken tot het gewenste kleurresultaat is bereikt.\nIngrediënten\nWater/Aqua/Eau,   Cetearyl Alcohol, Isopropyl Palmitate, Dicocoylethyl Hydroxyethylmonium   Methosulfate, Behenamidopropyl Dimethylamine, Behentrimonium Chloride,   Steartrimonium Chloride, Propylene Glycol, Dipropylene Glycol, Lactic Acid,   Isopropyl Alcohol, Panthenol, Ethylhexylglycerin, Citric Acid,   Phenoxyethanol, Fragrance/Parfum, Benzyl Alcohol, Citrus Aurantium Peel Oil,   Citrus Limon (Lemon) Peel Oil, Hexyl Cinnamal, Limonene, Linalool, Basic   Violet 2, HC Blue No.16"
  },
  "inferred_information": {
    "raw_ingredients": "WATER/AQUA/EAU, CETEARYL ALCOHOL, ISOPROPYL PALMITATE, DICOCOYLETHYL HYDROXYETHYLMONIUM METHOSULFATE, BEHENAMIDOPROPYL DIMETHYLAMINE, BEHENTRIMONIUM CHLORIDE, STEARTRIMONIUM CHLORIDE, PROPYLENE GLYCOL, DIPROPYLENE GLYCOL, LACTIC ACID, ISOPROPYL ALCOHOL, PANTHENOL, ETHYLHEXYLGLYCERIN, CITRIC ACID, PHENOXYETHANOL, FRAGRANCE/PARFUM, BENZYL ALCOHOL, CITRUS AURANTIUM PEEL OIL, CITRUS LIMON (LEMON) PEEL OIL, HEXYL CINNAMAL, LIMONENE, LINALOOL, BASIC VIOLET 2, HC BLUE NO.16.",
    "product_type": "Blond haar",
    "product_category": "Haarverzorging",
    "legal_grade": null,
    "ingredients": [
      "WATER/AQUA/EAU",
      "CETEARYL",
      "ALCOHOL",
      "ISOPROPYL",
      "PALMITATE",
      "DICOCOYLETHYL",
      "HYDROXYETHYLMONIUM",
      "METHOSULFATE",
      "BEHENAMIDOPROPYL",
      "DIMETHYLAMINE",
      "BEHENTRIMONIUM",
      "CHLORIDE",
      "STEARTRIMONIUM",
      "PROPYLENE",
      "GLYCOL",
      "DIPROPYLENE",
      "LACTIC",
      "ACID",
      "PANTHENOL",
      "ETHYLHEXYLGLYCERIN",
      "CITRIC",
      "PHENOXYETHANOL",
      "FRAGRANCE/PARFUM",
      "BENZYL",
      "CITRUS",
      "AURANTIUM",
      "PEEL",
      "OIL",
      "LIMON",
      "(LEMON)",
      "HEXYL",
      "CINNAMAL",
      "LIMONENE",
      "LINALOOL",
      "BASIC",
      "VIOLET",
      "2",
      "HC",
      "BLUE",
      "NO.16."
    ],
    "inci": {
      "cetearyl alcohol": [
        "99d4999e-c34d-40f3-b876-4d68bf0127cb",
        "194ab09b-a86f-40a8-9883-b63e577e0807",
        "b6b1f0e6-82aa-4c55-9203-a07e187d115e",
        "b63880e1-66b3-4e71-a08b-c3ee35090dd1",
        "d43587fc-d952-491a-9bba-b7ea483f591c",
        "3820d596-a346-4557-b1df-04af078f672d",
        "29d51668-d06e-4ca0-84a3-ec7965c67457",
        "fa9b3e4e-2d08-407a-8d12-86ef97f6f8d5",
        "66fd3a55-b090-413d-9de1-32fee95173a8",
        "7f249cb6-3b5c-4bb9-bd64-ec5e5333582d"
      ],
      "isopropyl palmitate": [
        "96f9d065-b8cc-488a-b098-0e038cee8bc9"
      ],
      "dicocoylethyl hydroxyethylmonium methosulfate": [
        "52d63aa5-a600-4631-bd32-97a5eeec2f08"
      ],
      "behenamidopropyl dimethylamine": [
        "ace0b55b-0928-4e86-95a0-e9bd1fbbdf6a",
        "71039fff-6a7b-45ae-ad0d-69a747bfe269",
        "40aeb9d7-1d7f-4120-a1eb-f603d574d2a4"
      ],
      "behentrimonium chloride": [
        "4e76b734-8f70-43a9-aa01-f4759629abc2"
      ],
      "steartrimonium chloride": [
        "17e465ce-c927-4711-aeb9-d63326df7029",
        "761aefc1-5b27-48b1-a966-d4ef192a5da0"
      ],
      "propylene glycol": [
        "0475616d-fb2f-49f8-8edf-06ad7de3aea6",
        "86c80ec2-3646-450a-88b7-06496837ed33",
        "d8f94954-1030-4913-931c-bce8987902b4",
        "ccd2e38a-fe36-44c4-847b-fbd8dc6d15f0",
        "ed2e48c4-f384-46db-90d7-19575fd073ec",
        "c0886eb7-d340-40a6-b45d-42b4154bbc7b",
        "4bc4664e-648f-4c62-8a62-17974acf2d1b",
        "21e4cdb5-c3fb-45ab-80cb-fd06007588fe",
        "0e29f9a6-8bea-465c-8d3c-a49db69ea5ec",
        "d2acf567-1e73-434f-ade2-7c2d80f019b1",
        "9a2782fc-1902-43dd-8b27-ca6ff570fb6e",
        "58788eac-3f14-4b87-bc69-46a742007cdf",
        "e7764972-8215-4649-ab24-58943e4998d0",
        "f3f17ff9-15a7-41a7-b45d-d73934a0e143",
        "36a68402-466f-4217-ab54-919310bb62ae",
        "61eced7b-e494-4572-b31a-374e4dac4296",
        "daa13929-9e73-43a7-b286-afa82ff82b8e",
        "b1ff25ae-8641-4aad-976c-b5af45fc1f10",
        "025e664c-24a0-483c-a765-48895834619e",
        "fe30f72e-411c-4dd5-83bc-17548efc634e",
        "5bb4471f-5e21-4ad3-b176-5eb8d75e84c6",
        "d2225586-fb3e-441c-8ded-eb57065e039e",
        "bbd9a35a-8dfe-43c9-b8ff-a7779a247bd4",
        "164c08f9-1e81-4ce3-b191-2527d64bfa07",
        "c82d8a5b-3b7e-4bf8-9241-a722f699e4f3",
        "04f64cdf-74e8-44bb-b63f-da653ea6634d",
        "6269ccaa-ed6a-4630-8e2f-dde789c44523",
        "7f391781-230c-4ac0-b0d3-b4a7d94cfd30",
        "a67ac8b4-4eb7-4e87-93be-618e94dc668a",
        "c37f0b50-0308-421a-abea-b921b33d0ade",
        "976face6-9c6b-4613-95fd-2a05b1c194ff",
        "63b2d911-7490-44fd-b222-810d709e3a6f",
        "9b3084e3-6426-4abb-ae58-16525f044fdc",
        "03546f5a-0c78-4079-b24d-bc31b6c1b99c",
        "33950008-878a-4579-8c1d-cae4468f19e2",
        "8e04a941-6771-4661-af43-591c0b0e48b0",
        "4605470f-324a-4d3c-8502-88c4f9394c72",
        "012e2222-b300-4d24-8fe6-3cb53ff08e55",
        "4e1309a5-f9a1-49d5-9203-d052347b1f32",
        "4b9d83fe-7cb2-4b28-a22a-7bf3217645c8",
        "19efa87e-c00c-4043-82c4-c36ddba02f21",
        "89075b50-afce-4fbe-9bf3-50e60c7457e1",
        "4216fdaa-e086-468f-aa6c-07ce5532183c",
        "a2693379-3bbd-4e95-922c-14f8d12a3312",
        "6547885f-6080-4ab4-a28a-2e576cbebf4c",
        "93782f1a-117c-49e6-8eca-9fe44b1ef6fc",
        "0e1c3690-8dbd-4a5d-a9b4-9f4a90b00202",
        "b5834156-0a62-4a3e-912c-3f59bf39def1",
        "9d180bc6-ba17-4c4a-bc09-1e783c32c2d9",
        "7b11537c-ff92-431b-b3ed-d15064b5233a",
        "81ae50d8-3e9f-4a84-92f6-fcf281643024",
        "19923ea2-b056-4de3-b498-ee97b9c93141",
        "c84869dd-6960-4740-a2d9-9ac835c7bfe1",
        "f05d071d-0643-4a22-bcc9-ed63c8cfe209",
        "996f6218-096d-4338-9e0b-cf6cb4e43f03",
        "be27fe2c-0ae2-4bb3-b443-67e35af4ba14",
        "194b21ff-5efc-4854-adbf-5c7ca315edc5",
        "1e0525e6-f5b4-4232-8c3a-b0a24842f705",
        "f41ad903-e23a-4a38-a7bd-1551226ac9dc",
        "1480f95d-9343-4f09-bf68-4ce68b5cb5c7",
        "a5f93e9a-b374-4492-99af-9d9226a20bb5",
        "353eb65f-024e-4554-9535-ae61676ab671",
        "4f345ae4-4989-4790-ac69-9e3918f3521f",
        "5126d2ef-3697-4120-8a6e-7408fc81e4ba",
        "a95760b3-8c11-4f8d-886d-685b5be0aacb",
        "9a45d3dc-78b5-47d4-8f77-0c987a173fac",
        "bd170ed2-149f-4d02-94ce-298badf374e1",
        "ea43ce54-f496-4bfe-a395-8c09ef8103fa",
        "18f0403d-ecdc-4350-a087-f4d72b51bcca",
        "af9db1fe-3105-4b75-b365-b5d5b9fd0bfe",
        "c0e76431-6fd9-4b5a-b553-dd9e23b57fe3",
        "455a77f6-13a7-47d9-a1eb-e7bedcccecf8",
        "f3a6bf2b-7711-4e31-af81-8cff6c97e17a",
        "ae860483-7aba-4421-81c0-92750499d424",
        "4084cb97-fa80-4f3d-a7fd-f132a8d7f048",
        "362b54c6-6bc4-44ab-a33a-3408bbe16550",
        "29ee2aad-308f-434f-a8c5-2ded7cac1769",
        "e9cff5cb-71ab-464e-86ba-f1b3e966ae60",
        "c1652f14-4890-42fa-bd58-35a94a4d7419",
        "156236a0-9133-417e-9435-191475f6005d",
        "5d841d48-794c-4e5b-b61a-b936ddb94748",
        "ea2989e6-beac-4ab3-9213-384e9fadbf68",
        "fe38a43c-7a8c-4876-b504-4ce1ee8547a8",
        "66b6aa6f-f41f-4df3-b087-cebd2f436a44",
        "63f805b8-f323-4bf3-92c5-95434e3d634a",
        "1790fb1c-c579-4868-a3dd-c2c24d5d8f6c",
        "c9611ab5-4dc7-443a-9d70-eb661a32b822",
        "62ca884d-1215-46af-abf1-daa2aae7fe2c",
        "07e225c5-5ee3-4573-abf8-625c5527e439",
        "4b53d23e-00ee-42c1-b354-9ca2a3b569d7",
        "525d309f-e047-4606-8520-e4155fc301e9",
        "0cdd0573-a720-4662-9370-5359bc86fa5d",
        "a4300e48-aba4-4130-ab9c-5152fd015d45",
        "71403259-7a48-4e5b-9456-3fd81381262b",
        "73a39bec-047d-40d0-9351-4cafd56bf2da",
        "8a848047-7a6c-4549-ba76-9d3c0288ace4",
        "f9419a0f-4b69-4519-bab6-e30374916e84",
        "c96996d1-bd87-4f42-bf98-d1c95f8d86fa",
        "8046d555-56c4-4643-a05f-6b3bb7088dda",
        "c58bae11-e81a-49c5-b9e7-cccac4d924e9"
      ],
      "dipropylene glycol": [
        "1ffb6c84-2c44-4320-9cff-1e8f1bdb76c0",
        "c0886eb7-d340-40a6-b45d-42b4154bbc7b",
        "ab618234-98c2-4c12-9dda-8334ec1ea2cb",
        "159a693a-b7c8-4734-ace4-19110b5398d8",
        "c0068a29-6c8b-44ec-8a94-2df474d042bf",
        "6f21aa7e-de9a-483a-8808-8f2f4d7cf5c8",
        "3f4d6b44-cde0-447c-b3cf-140a9e375e7c",
        "41ca8e1c-7f48-47d8-bc09-03a226d15cd2",
        "e0e63888-fb7a-4344-acf6-b9649700355c",
        "baa20a0a-692f-4b38-9c68-1c117bc91fbc",
        "435bf2fc-1b7d-4e28-9223-33cc3386dcb5",
        "bd3bd1f8-5ac3-4a6c-944f-5cf6ba0e4ec9",
        "34e33887-b77c-4e7f-b7b9-66eb02cc6161",
        "35ba144c-0a46-4f4c-9a3b-df176e64eaec"
      ],
      "lactic acid": [
        "366b5960-4dd9-4f4a-9b25-d670d30f3b6f",
        "d31a8d26-d71a-4959-9159-5c42b8cfe549",
        "03ff8841-a4ee-4792-a560-c816495970d8",
        "c03df1c9-18b7-43f1-b065-61b5a27bb900",
        "97794d0c-d395-4644-89b9-2cdbaf0f81b3",
        "d2a01d1c-8cfb-4e75-98e6-6d62ba83c4a6",
        "262b545e-8ced-4703-b90b-36f88fe48724",
        "f1547e9b-d224-4c4b-8d9f-9a7eb7d6cc21",
        "cb9201e0-9710-4c88-9134-d677ae0ba208",
        "c23e32ec-de65-4887-9545-bae9837dc891",
        "727c38c1-4f8c-4228-9124-4c61e4794487",
        "b749e066-d540-4a3d-88b4-ee45517f0aac",
        "9708cee6-39e8-49e2-989e-f27e82682169",
        "4f252bb3-4105-43ee-8ef7-8b00337afd75",
        "3f6adfd5-0f1c-465c-a31b-b5748148070e",
        "d8638571-2c24-4db5-b294-ff1159ca4da7",
        "bf48a709-95ae-42bf-be72-29253b54ea58",
        "8e99afe3-f248-4c04-ade7-689900590462",
        "689f373a-8170-49b1-aff0-50d1f4c8b49a",
        "3a4b30a5-fd78-4deb-a058-360ddebeb98d",
        "2be95a51-4278-4661-82c2-66e6a1d80c59"
      ],
      "isopropyl alcohol": [
        "a1b27b72-3de9-441c-a033-deda607a8d81",
        "93008b25-d9c9-4b37-ab27-e827d3b49f96",
        "70d92e7b-a00c-4753-9dd6-4db8493aeb78",
        "26accb1a-5bd2-4ee8-a2c4-4165872732dc",
        "d2a94c1b-12f1-4fa3-9eea-4362b7389862",
        "bb97f2d1-eb35-48a3-9dbc-2567d74d2a91",
        "1824cf47-b365-48f1-8faf-015da9d072c2"
      ],
      "panthenol": [
        "dae58323-b8ab-4d71-a0fb-2c610738f58b",
        "02b5654c-8fdf-44f4-a178-8f505b61ef9d",
        "886347a6-7c3f-44ab-a5b9-7e249701c871",
        "b7d7e892-c53d-4bad-89d6-81185529ec3b",
        "352d78b1-7087-4198-bc6d-bbb00d2f9b97",
        "a608b5ca-65f9-451d-977c-441fdd3582d9",
        "c71868c2-5111-4dde-ba34-b26a8eddd7e1",
        "d4f863e5-3a9b-4b81-9516-be777fb2806e",
        "d9cc16cc-9b12-4305-94af-2876133604c3",
        "8bd07fd2-c550-4ac8-a955-65957ebef28b"
      ],
      "ethylhexylglycerin": [
        "c4da9c7a-3487-4c25-863c-9ddd013282b5",
        "e15fd8ce-b1a3-4b57-a5ec-70b85dd949b4"
      ],
      "citric acid": [
        "398b79ca-fc64-43b5-bf15-956e6239c1db",
        "1480f95d-9343-4f09-bf68-4ce68b5cb5c7",
        "4f345ae4-4989-4790-ac69-9e3918f3521f",
        "a15f0ed1-c032-4545-b545-31b808440ebe",
        "0475616d-fb2f-49f8-8edf-06ad7de3aea6",
        "114a0f38-02c6-4b8e-9497-4a7123db4b99",
        "92fdfdd5-7cf8-4c76-9c54-8d01be21e806",
        "2ae3cc68-1096-41c2-8368-1288163e2c75",
        "50ed5817-b951-4e9e-9bd1-06713bd3c42a",
        "efb40140-403c-48f0-b76f-a54cc3313786",
        "e30e18c1-47d2-4558-815f-6902599aa7f2",
        "3fd7f7bf-ff0e-4fe8-bcf1-fdec2f388e71",
        "dfbffaa1-9498-4c09-83ba-071285866fca",
        "14c5d1bf-54ae-4e14-8439-c9297a9561a5",
        "b30a0a54-bd97-4cdc-b193-b15f41b9aa9d",
        "0bc748a1-0dfe-4bd6-90a4-7424a130dcba",
        "b3426c0c-001b-4cf4-ba7f-1b93964598e4",
        "380e8aa3-149d-497f-973e-8d8898ac05a4",
        "dda20ee1-8364-4540-92b5-bbd50fa99c85",
        "cc3cfaeb-3457-44f7-8961-61598a2deda5",
        "00b6e815-ef31-425b-8c98-9aa6d426f696",
        "173aa29a-c8ac-404b-b971-119e702bbb54",
        "0085caa1-70bf-4a6d-9845-62d38ee1de03",
        "29d51668-d06e-4ca0-84a3-ec7965c67457",
        "f9c6d0eb-eb39-4671-8fe2-a2e6e4594e66",
        "16841e6c-abfc-4300-87cb-072d880bb571",
        "21e68034-a1bb-442c-b382-bf8024b87500",
        "53bcef98-1ed3-4d7a-9335-739e04539609",
        "879dfe97-f5b0-409b-b3ab-7e45038f373b",
        "2d50705f-7aab-497a-9eb1-949bfacf4e2e",
        "f38c86bd-f573-4998-bc93-0ae4477dac25",
        "09cfe452-a81c-440f-9b2f-dde3e79cbe88",
        "e9589e3c-67f5-49cf-8635-2c77ca5c69fc",
        "3f4d6b44-cde0-447c-b3cf-140a9e375e7c",
        "7b4c4daf-505f-4391-86e9-854b747710e3",
        "a59d320f-ad7e-4f45-bb78-3a39371f5b2f",
        "ecdae489-cedf-4392-8c60-3fa9e0ccad15",
        "a2a8a8f3-e6e5-41fe-b8e0-8e96c6ec03ea"
      ],
      "phenoxyethanol": [
        "f8f3a6ab-5656-4d9a-a085-729e03a7376d",
        "4e24ebd7-ace5-457a-a1c2-da84869f28ac",
        "2f7d305c-12a6-440c-9467-1c445020bb17"
      ],
      "benzyl alcohol": [
        "43b6ac65-f60d-42b8-8d5e-72d73a17cce5",
        "01d7ff39-2dc3-4f03-bae0-3dfca710120a",
        "939e6a7b-1a91-44f4-9f60-4e70985d229a",
        "b8bed1f8-a18b-4f12-ada2-664e686fddd7",
        "ba0d9117-68cd-47ec-943e-ee22d1f97e0c",
        "5df0262e-332d-4c98-87f5-4257ba216224",
        "a24b079a-84ee-4fb4-87b7-8c368822058c",
        "14619b8e-220c-424e-8752-9c511215fb8b",
        "c753e955-bd9a-4483-a23a-b674ac4c8898",
        "0ee058c6-2cba-4bc4-9dcb-5b1998258e33",
        "edd5f200-f6ba-46b3-a266-bf0764c5955a",
        "873dab8c-c57d-483f-83f3-6400b2954151",
        "a59d320f-ad7e-4f45-bb78-3a39371f5b2f",
        "0bb3c0fe-0d9e-4758-83e0-eb26b83b937b",
        "2c093be3-34aa-4d45-bd6a-906848433a08",
        "8367fb00-ef11-484b-9107-e06cdce50896",
        "a60f276c-63f7-48c3-8b9f-f3e9f548cc5b",
        "d58d7b28-55b5-4f18-93e5-d029c86de7ea",
        "3cf07fbd-ee1f-4dfe-841c-03b81ed71e52",
        "6535dffb-5c2f-4d7d-94a6-2a7566d63543",
        "995a8f43-ecad-4e03-a475-bbdfedad1560",
        "dbe208ed-5f66-4ada-acca-07b4d2017273",
        "c7d8e0ee-63a4-47cc-836b-3f612057f606"
      ],
      "citrus aurantium peel oil": [
        "319a7f33-e7c2-4980-893c-95401d36c377",
        "f0fc6896-88e3-4c26-9653-fe2b7e78874c",
        "b747f753-b493-47a5-b0d3-4d3ec981e273",
        "a923c1c8-494d-4330-9bff-3e8b24f17b00",
        "f9c05970-20d5-47a4-8093-098a52a53874",
        "ecf6ef2d-4da6-4ff8-a1d0-d29422d24e3a",
        "a4931990-2a2a-46dc-a740-46703fe88c6d",
        "6627e41a-1b9d-4622-89b3-1964337768d2",
        "67734a62-d120-45e1-ba29-4a62454d9224",
        "d657011d-cff1-41f2-8f9f-fe37c7a11a84",
        "dcbdaa4c-4fbc-4473-987a-6d33558a5c19",
        "a64c558c-1c8a-4f75-8411-0108578fb4f6"
      ],
      "citrus limon (lemon) peel oil": [
        "01e2fc89-8c20-410e-b9b6-cd5e3d7f59ae",
        "410b8409-6325-430b-b29f-47b29bc853dd"
      ],
      "hexyl cinnamal": [
        "dfe28bfe-bd94-4e13-9f73-24aba98e5505"
      ],
      "limonene": [
        "d9a853fb-831a-4f8e-a3f5-d57b976d9c88",
        "23d540ea-0079-4c28-8b69-10033f69f535",
        "d61c4bec-0b4d-4e48-aef5-a218fea8b8cc",
        "094b1ce3-9584-4c45-b567-8123e10e7033",
        "77c4653c-3430-4779-bdd8-d76199258418",
        "dd0b9281-85f3-43f2-b398-855b0154e62a",
        "65222645-e4f3-41ab-aba8-9c8715c879bd",
        "59c3e02e-9dda-4c79-a55e-14af2cdcf062",
        "2fd55649-0293-4f5a-a737-e487ede48da7",
        "2f9203ba-2582-4f8f-a9d3-6127a0b3f84b",
        "fcb99a35-7fdb-447a-9c32-0754d66b463b",
        "57bf7d48-3909-49da-a340-cc2a2164759c",
        "e99411e7-a980-4d98-a824-64d3ba18b1ce",
        "b9d71c6d-39c6-47c0-ade3-b681e8f343f2",
        "f0386f6b-f59b-49a8-a468-5c77e8a8188e",
        "7f9f30da-c884-4e7d-ba53-2b8eb25b55be",
        "cffcb078-879d-49cd-964d-2166ba4444e3",
        "c520b563-610e-4e05-be57-11ba1a7c203a",
        "67734a62-d120-45e1-ba29-4a62454d9224",
        "6166f166-7a24-446d-b5a3-c7eb8d60fb7f",
        "a209d30f-e08c-4245-b4a8-a1812d41feef",
        "ebdb8cd5-9a2a-446d-b207-9c6ea3bb4e2b",
        "d489e0ea-9a81-4b1d-b8bc-5502db5adb42",
        "37922c57-22ba-47ac-86a5-185e7d7702fb",
        "5fd73f7d-090a-41e9-9cf8-ec2d82359ab1",
        "f43f6f59-9dfd-4a87-b632-82dadb6e5796",
        "29a385e8-9ff6-43f0-8eac-8788fb368de3",
        "e3c609ab-4b8a-4089-89b0-18279e3f2837",
        "cfcdbaea-0fbc-4c60-9c38-021736c36bb5",
        "0e1e8e38-fc2e-4ce7-84f9-4dce5df36518",
        "dcbdaa4c-4fbc-4473-987a-6d33558a5c19",
        "d93d671b-3419-4680-8269-60583ec9ac0e",
        "caf20e39-06fb-43bf-8453-7a582cc1d1d4"
      ],
      "linalool": [
        "8f47a2fa-c519-434c-8bb9-8385cf05fea5",
        "c396cf4a-6357-436d-8d55-fb24f9961d3d",
        "8d5a2513-3e2c-44f1-8f85-624d6342866f",
        "0018acfb-f2a4-4538-8f28-f8af71041bb9",
        "f2357e58-0181-41f6-b80b-457d1f55ee91",
        "a19ecbd9-8ced-402a-85d8-9e341468e55f",
        "99634e65-3bfd-420f-a5b9-7094dc581270",
        "72a74c17-4c98-4ee7-a58a-7d5ff3942560",
        "cbc4a314-95f5-4345-98cc-61b2d87bf963",
        "f5f287c8-50f4-4c93-8b0d-41c89b985347",
        "ccd1c9bf-9835-4c02-bb80-d3791d4f6690",
        "7b037553-1d27-4931-8108-84efc7f93f6a",
        "c2d79f26-662b-4480-b669-afdef300ad6e",
        "a803ace3-7f88-4b6f-aa4a-0b4119093446",
        "67734a62-d120-45e1-ba29-4a62454d9224",
        "d489e0ea-9a81-4b1d-b8bc-5502db5adb42",
        "d61c4bec-0b4d-4e48-aef5-a218fea8b8cc",
        "29a385e8-9ff6-43f0-8eac-8788fb368de3",
        "dcbdaa4c-4fbc-4473-987a-6d33558a5c19",
        "d93d671b-3419-4680-8269-60583ec9ac0e"
      ],
      "basic violet 2": [
        "2d34c014-91f9-4f21-8c6b-35048316fe43",
        "c762b2c9-4f97-46ae-9168-b57c27bf286f",
        "fca4da58-32b0-49ef-baf2-8122060587b1"
      ],
      "hc blue no.16.": [
        "18fde487-baae-4f29-a3ee-380787a37894"
      ]
    }
  },
  "additional_information": {
    "id": "120600140"
  }
}